xemail.py
EmailChunking-0.1.dev2.dist-info/METADATA
EmailChunking-0.1.dev2.dist-info/WHEEL
EmailChunking-0.1.dev2.dist-info/top_level.txt
EmailChunking-0.1.dev2.dist-info/RECORD
