Metadata-Version: 2.1
Name: EmailChunking
Version: 0.1.dev2
Summary: UNKNOWN
Home-page: UNKNOWN
Author: UNKNOWN
Author-email: UNKNOWN
License: Creative Commons Attribution-Noncommercial-Share Alike license
Platform: UNKNOWN
Requires-Dist: spacy (==1.9.0)
